MANIFEST.in
README.md
setup.py
filmsontonight/__init__.py
filmsontonight/__main__.py
filmsontonight/csv_handler.py
filmsontonight/imdb.py
filmsontonight/viewfilm.py
filmsontonight.egg-info/PKG-INFO
filmsontonight.egg-info/SOURCES.txt
filmsontonight.egg-info/dependency_links.txt
filmsontonight.egg-info/not-zip-safe
filmsontonight.egg-info/requires.txt
filmsontonight.egg-info/top_level.txt