Metadata-Version: 1.1
Name: filmsontonight
Version: 0.1
Summary: Scrapes viewfilm.net to get the films on that night
Home-page: http://github.com/jdbaldry/FilmsOnTonight
Author: Jack Baldry
Author-email: jdbaldry@gmail.com
License: MIT
Platform: UNKNOWN
Classifier: Development Status :: 3 - Alpha
Classifier: License :: OSI Approved :: MIT License
Classifier: Programming Language :: Python :: 2.7
